mv0401/__init__.py
mv0401/mv0401.py
mv0401/test_mv0401.py
mv0401/test_responses.py
mv0401_multiviewer-0.1.0.dist-info/licenses/LICENSE
mv0401_multiviewer-0.1.0.dist-info/METADATA
mv0401_multiviewer-0.1.0.dist-info/WHEEL
mv0401_multiviewer-0.1.0.dist-info/top_level.txt
mv0401_multiviewer-0.1.0.dist-info/RECORD
