Metadata-Version: 2.4
Name: MV0401-Multiviewer
Version: 0.1.0
Summary: Python Telnet wrapper for the MV0401 device
Author: Justin Faulk
License-Expression: MIT
Requires-Python: >=3.13
License-File: LICENSE
Requires-Dist: telnetlib-313-and-up
Dynamic: license-file
